{
    "m_Version": 24,
    "Enabled": 1,
    "FormationScale": -1.0,
    "DespawnTime": 10.0,
    "RespawnTime": 10.0,
    "MinDistRadius": 400.0,
    "MaxDistRadius": 1100.0,
    "DespawnRadius": 1400.0,
    "AccuracyMin": 0.44999998807907107,
    "AccuracyMax": 0.4999999701976776,
    "ThreatDistanceLimit": -1.0,
    "NoiseInvestigationDistanceLimit": -1.0,
    "DamageMultiplier": -1.0,
    "DamageReceivedMultiplier": -1.0,
    "LoadBalancingCategories": {
        "Global": [],
        "Example": [],
        "Quest": [
            {
                "MinPlayers": 0,
                "MaxPlayers": 255,
                "MaxPatrols": -8
            }
        ],
        "ObjectPatrol": [
            {
                "MinPlayers": 0,
                "MaxPlayers": 255,
                "MaxPatrols": -4
            }
        ],
        "HelicopterWreck": [
            {
                "MinPlayers": 0,
                "MaxPlayers": 255,
                "MaxPatrols": -4
            }
        ],
        "ContaminatedArea": [],
        "Patrol": []
    },
    "ObjectPatrols": [
        {
            "Name": "",
            "Persist": 0,
            "Faction": "West",
            "Formation": "Wall",
            "FormationScale": -1.0,
            "FormationLooseness": 0.0,
            "Loadout": "A_Civ_NOGOVO",
            "Units": [],
            "NumberOfAI": 1,
            "Behaviour": "ALTERNATE",
            "LootingBehaviour": "",
            "Speed": "JOG",
            "UnderThreatSpeed": "JOG",
            "CanBeLooted": 1,
            "UnlimitedReload": 1,
            "SniperProneDistanceThreshold": 0.0,
            "AccuracyMin": 0.3199999928474426,
            "AccuracyMax": 0.3799999952316284,
            "ThreatDistanceLimit": -1.0,
            "NoiseInvestigationDistanceLimit": -1.0,
            "DamageMultiplier": -1.0,
            "DamageReceivedMultiplier": -1.0,
            "CanBeTriggeredByAI": 0,
            "MinDistRadius": -1.0,
            "MaxDistRadius": -1.0,
            "DespawnRadius": -1.0,
            "MinSpreadRadius": 15.0,
            "MaxSpreadRadius": 120.0,
            "Chance": 1.0,
            "WaypointInterpolation": "",
            "DespawnTime": -1.0,
            "RespawnTime": 900.0,
            "LoadBalancingCategory": "",
            "ClassName": "StaticObj_PartyTent"
        },
        {
            "Name": "",
            "Persist": 0,
            "Faction": "West",
            "Formation": "Wall",
            "FormationScale": -1.0,
            "FormationLooseness": 0.0,
            "Loadout": "A_Civ308",
            "Units": [],
            "NumberOfAI": 1,
            "Behaviour": "ALTERNATE",
            "LootingBehaviour": "DEFAULT",
            "Speed": "JOG",
            "UnderThreatSpeed": "JOG",
            "CanBeLooted": 1,
            "UnlimitedReload": 1,
            "SniperProneDistanceThreshold": 0.0,
            "AccuracyMin": 0.3199999928474426,
            "AccuracyMax": 0.3799999952316284,
            "ThreatDistanceLimit": 500.0,
            "NoiseInvestigationDistanceLimit": -1.0,
            "DamageMultiplier": -1.0,
            "DamageReceivedMultiplier": -1.0,
            "CanBeTriggeredByAI": 0,
            "MinDistRadius": 400.0,
            "MaxDistRadius": 1100.0,
            "DespawnRadius": 1300.199951171875,
            "MinSpreadRadius": 50.0,
            "MaxSpreadRadius": 150.0,
            "Chance": 1.0,
            "WaypointInterpolation": "",
            "DespawnTime": -1.0,
            "RespawnTime": 900.0,
            "LoadBalancingCategory": "",
            "ClassName": "ExpansionAirdropContainer"
        },
        {
            "Name": "",
            "Persist": 0,
            "Faction": "West",
            "Formation": "Wall",
            "FormationScale": -1.0,
            "FormationLooseness": 0.0,
            "Loadout": "A_Param_556",
            "Units": [],
            "NumberOfAI": 1,
            "Behaviour": "ALTERNATE",
            "LootingBehaviour": "DEFAULT",
            "Speed": "JOG",
            "UnderThreatSpeed": "JOG",
            "CanBeLooted": 1,
            "UnlimitedReload": 1,
            "SniperProneDistanceThreshold": 0.0,
            "AccuracyMin": 0.3199999928474426,
            "AccuracyMax": 0.3799999952316284,
            "ThreatDistanceLimit": 500.0,
            "NoiseInvestigationDistanceLimit": -1.0,
            "DamageMultiplier": -1.0,
            "DamageReceivedMultiplier": -1.0,
            "CanBeTriggeredByAI": 0,
            "MinDistRadius": 400.0,
            "MaxDistRadius": 1100.0,
            "DespawnRadius": 1300.199951171875,
            "MinSpreadRadius": 50.0,
            "MaxSpreadRadius": 150.0,
            "Chance": 1.0,
            "WaypointInterpolation": "",
            "DespawnTime": -1.0,
            "RespawnTime": 900.0,
            "LoadBalancingCategory": "",
            "ClassName": "ExpansionAirdropContainer_Blue"
        },
        {
            "Name": "",
            "Persist": 0,
            "Faction": "West",
            "Formation": "Wall",
            "FormationScale": -1.0,
            "FormationLooseness": 0.0,
            "Loadout": "A_Param_556",
            "Units": [],
            "NumberOfAI": 1,
            "Behaviour": "ALTERNATE",
            "LootingBehaviour": "DEFAULT",
            "Speed": "JOG",
            "UnderThreatSpeed": "JOG",
            "CanBeLooted": 1,
            "UnlimitedReload": 1,
            "SniperProneDistanceThreshold": 0.0,
            "AccuracyMin": 0.3199999928474426,
            "AccuracyMax": 0.3799999952316284,
            "ThreatDistanceLimit": 500.0,
            "NoiseInvestigationDistanceLimit": -1.0,
            "DamageMultiplier": -1.0,
            "DamageReceivedMultiplier": -1.0,
            "CanBeTriggeredByAI": 0,
            "MinDistRadius": 400.0,
            "MaxDistRadius": 1100.0,
            "DespawnRadius": 1300.199951171875,
            "MinSpreadRadius": 50.0,
            "MaxSpreadRadius": 150.0,
            "Chance": 1.0,
            "WaypointInterpolation": "",
            "DespawnTime": -1.0,
            "RespawnTime": 900.0,
            "LoadBalancingCategory": "",
            "ClassName": "ExpansionAirdropContainer_Olive"
        },
        {
            "Name": "",
            "Persist": 0,
            "Faction": "West",
            "Formation": "Wall",
            "FormationScale": -1.0,
            "FormationLooseness": 0.0,
            "Loadout": "A_Civ308",
            "Units": [],
            "NumberOfAI": 1,
            "Behaviour": "ALTERNATE",
            "LootingBehaviour": "DEFAULT",
            "Speed": "JOG",
            "UnderThreatSpeed": "JOG",
            "CanBeLooted": 1,
            "UnlimitedReload": 1,
            "SniperProneDistanceThreshold": 0.0,
            "AccuracyMin": 0.3199999928474426,
            "AccuracyMax": 0.3799999952316284,
            "ThreatDistanceLimit": 500.0,
            "NoiseInvestigationDistanceLimit": -1.0,
            "DamageMultiplier": -1.0,
            "DamageReceivedMultiplier": -1.0,
            "CanBeTriggeredByAI": 0,
            "MinDistRadius": 400.0,
            "MaxDistRadius": 1100.0,
            "DespawnRadius": 1300.199951171875,
            "MinSpreadRadius": 20.0,
            "MaxSpreadRadius": 40.0,
            "Chance": 1.0,
            "WaypointInterpolation": "",
            "DespawnTime": -1.0,
            "RespawnTime": 900.0,
            "LoadBalancingCategory": "",
            "ClassName": "ExpansionAirdropContainer_Basebuilding"
        },
        {
            "Name": "",
            "Persist": 0,
            "Faction": "East",
            "Formation": "Wall",
            "FormationScale": -1.0,
            "FormationLooseness": 1.0,
            "Loadout": "Alpine_556",
            "Units": [],
            "NumberOfAI": 2,
            "Behaviour": "ALTERNATE",
            "LootingBehaviour": "",
            "Speed": "JOG",
            "UnderThreatSpeed": "JOG",
            "CanBeLooted": 1,
            "UnlimitedReload": 1,
            "SniperProneDistanceThreshold": 0.0,
            "AccuracyMin": 0.3199999928474426,
            "AccuracyMax": 0.3799999952316284,
            "ThreatDistanceLimit": -1.0,
            "NoiseInvestigationDistanceLimit": -1.0,
            "DamageMultiplier": -1.0,
            "DamageReceivedMultiplier": -1.0,
            "CanBeTriggeredByAI": 0,
            "MinDistRadius": -1.0,
            "MaxDistRadius": -1.0,
            "DespawnRadius": -1.0,
            "MinSpreadRadius": 5.0,
            "MaxSpreadRadius": 125.0,
            "Chance": 1.0,
            "WaypointInterpolation": "",
            "DespawnTime": -1.0,
            "RespawnTime": -2.0,
            "LoadBalancingCategory": "HelicopterWreck",
            "ClassName": "Wreck_UH1Y"
        }
    ],
    "Patrols": [
        {
            "Name": "",
            "Persist": 0,
            "Faction": "West",
            "Formation": "File",
            "FormationScale": -1.0,
            "FormationLooseness": 1.0,
            "Loadout": "A_Civ_556",
            "Units": [],
            "NumberOfAI": -4,
            "Behaviour": "LOOP",
            "LootingBehaviour": "DEFAULT",
            "Speed": "JOG",
            "UnderThreatSpeed": "JOG",
            "CanBeLooted": 1,
            "UnlimitedReload": 1,
            "SniperProneDistanceThreshold": 0.0,
            "AccuracyMin": 0.2500000298023224,
            "AccuracyMax": 0.3199999928474426,
            "ThreatDistanceLimit": 500.0,
            "NoiseInvestigationDistanceLimit": -1.0,
            "DamageMultiplier": -1.0,
            "DamageReceivedMultiplier": -1.0,
            "CanBeTriggeredByAI": 0,
            "MinDistRadius": 400.0,
            "MaxDistRadius": 1200.0,
            "DespawnRadius": 1500.199951171875,
            "MinSpreadRadius": 0.10000000149011612,
            "MaxSpreadRadius": 100.0999984741211,
            "Chance": 1.0,
            "WaypointInterpolation": "",
            "DespawnTime": -1.0,
            "RespawnTime": 1200.0,
            "LoadBalancingCategory": "",
            "UseRandomWaypointAsStartPoint": 1,
            "Waypoints": [
                [
                    5543.2900390625,
                    11.583100318908692,
                    9875.3896484375
                ],
                [
                    5440.259765625,
                    12.497400283813477,
                    9836.7998046875
                ],
                [
                    5354.830078125,
                    18.16790008544922,
                    9798.150390625
                ],
                [
                    5320.2001953125,
                    18.860000610351564,
                    9749.830078125
                ],
                [
                    5287.919921875,
                    18.368000030517579,
                    9721.01953125
                ],
                [
                    5233.4501953125,
                    11.23639965057373,
                    9765.33984375
                ],
                [
                    5339.509765625,
                    5.631589889526367,
                    9890.0302734375
                ],
                [
                    5518.27001953125,
                    5.072649955749512,
                    9970.2900390625
                ],
                [
                    5535.6201171875,
                    9.5635404586792,
                    9921.1796875
                ]
            ]
        },
        {
            "Name": "",
            "Persist": 0,
            "Faction": "West",
            "Formation": "Wall",
            "FormationScale": -1.0,
            "FormationLooseness": 0.0,
            "Loadout": "Grunt",
            "Units": [],
            "NumberOfAI": 2,
            "Behaviour": "LOOP",
            "LootingBehaviour": "DEFAULT",
            "Speed": "JOG",
            "UnderThreatSpeed": "JOG",
            "CanBeLooted": 1,
            "UnlimitedReload": 1,
            "SniperProneDistanceThreshold": 0.0,
            "AccuracyMin": 0.3199999928474426,
            "AccuracyMax": 0.3799999952316284,
            "ThreatDistanceLimit": 500.0,
            "NoiseInvestigationDistanceLimit": -1.0,
            "DamageMultiplier": -1.0,
            "DamageReceivedMultiplier": -1.0,
            "CanBeTriggeredByAI": 0,
            "MinDistRadius": 400.0,
            "MaxDistRadius": 1200.0,
            "DespawnRadius": 1500.199951171875,
            "MinSpreadRadius": 0.10000000149011612,
            "MaxSpreadRadius": 50.099998474121097,
            "Chance": 1.0,
            "WaypointInterpolation": "",
            "DespawnTime": -1.0,
            "RespawnTime": 1200.0,
            "LoadBalancingCategory": "",
            "UseRandomWaypointAsStartPoint": 1,
            "Waypoints": [
                [
                    7094.8798828125,
                    2.6600000858306886,
                    7623.009765625
                ],
                [
                    7161.169921875,
                    2.6600000858306886,
                    7330.43017578125
                ],
                [
                    7215.5498046875,
                    2.6600000858306886,
                    7035.39013671875
                ],
                [
                    7161.169921875,
                    2.6600000858306886,
                    7330.43017578125
                ]
            ]
        }
    ]
}